setup.py
angellist/__init__.py
python_angellist.egg-info/PKG-INFO
python_angellist.egg-info/SOURCES.txt
python_angellist.egg-info/dependency_links.txt
python_angellist.egg-info/not-zip-safe
python_angellist.egg-info/readme.txt
python_angellist.egg-info/requires.txt
python_angellist.egg-info/top_level.txt