Metadata-Version: 1.1
Name: python-angellist
Version: 0.5
Summary: Light wrapper around AngelList API
Home-page: https://github.com/sandeepbhaskar/python-angellist
Author: Sandeep Bhaskar
Author-email: sandeep.bhaskar19@gmail.com
License: MIT
Platform: UNKNOWN
Classifier: Development Status :: 3 - Alpha
Classifier: Environment :: Web Environment
Classifier: Intended Audience :: Developers
Classifier: Operating System :: OS Independent
Classifier: Programming Language :: Python
